---
title: Java基础
date: 2020-08-30 22:30:04
permalink: /pages/java_base
categories:
  - 后端
  - Java
tags:
  - Java
author:
  name: 詹佳斌
  link: https://github.com/zhanjiabin
---
Java是一门面向对象编程语言，不仅吸收了C++语言的各种优点，还摒弃了C++里难以理解的多继承、指针等概念，因此Java语言具有功能强大和简单易用两个特征
<!-- more -->
# Java基础

## 一.面向对象

### 1.什么是面向对象？

1. OOP（Object Oriented Programming）：面向对象编程。
2. OOD（Object Oriented Design）：面向对象设计。
3. OOA（Object Oriented Analysis）：面向对象分析。

### 2.面向对象和面向过程的区别是什么？

**面向过程**
优点：性能比面向对象高，因为类调用时需要实例化，开销比较大，比较消耗资源：比如单片机、嵌入式开发、Linux/Unix等一般采用面向过程开发。

缺点：没有面向对象易维护、易复用、易扩展。

**面向对象**
优点：易维护、易复用、易扩展，由于面向对象有封装、继承、多态等特性，可以设计出低耦合的系统，使得系统更加灵活、更加易于维护。

缺点：性能比面向过程低。

**举例**

蛋炒饭和盖浇饭

### 3.面向对象的基本特征？

三大基本特性：封装、继承、多态。

**封装** 
  封装，也就是把客观事物封装成抽象的类，并且类可以把自己的数据和方法只让可信的类或者对象操作，对不可信的进行信息隐藏。

**封装示例代码：**

```java
public class Person {

    private String name;

    private Integer age;

    Person(){

    }

    Person(String name,Integer age){
        this.name = name;
        this.age = age;
    }

    public String getName() {
        return name;
    }

    public Integer getAge() {
        return age;
    }

    public void setName(String name) {
        this.name = name;
    }

    public void setAge(Integer age) {
        this.age = age;
    }

    @Override
    public String toString() {
        return "Person{" +
                "name='" + name + '\'' +
                ", age=" + age +
                '}';
    }

    public static void main(String[] args) {
        Person person = new Person("corona",24);
        System.out.println(person.toString());
    }
}

输出结果：Person{name='corona', age=24}


```

要调用Person的方法或属性，必须先new一个Person。

**继承**
  继承是指这样一种能力：它可以使用现有类的所有能力，并在无需重新编写原来类的情况下对这些功能进行扩展，通过继承创建的新类称为[子类]或[派生类]，被继承的类称为[基类]、[父类]或[超类]。
  要实现继承，可以通过**extends**关键字来实现。

**继承示例代码：**

```java
public class Student extends Person {

    private Integer score;

    Student(){

    }

    Student(String name, Integer age, Integer score) {
        super(name, age);
        this.score = score;
    }

    public Integer getScore() {
        return score;
    }

    public void setScore(Integer score) {
        this.score = score;
    }

    @Override
    public String toString() {
        return "Student{" +
                "score=" + score +
                '}';
    }

    public static void main(String[] args) {
        Student student = new Student("corona", 24, 100);
        System.out.println(student.getName() + "今年" + student.getAge() + "岁，" + "考试得了" + student.getScore() + "分。");
    }
}

输出结果：corona今年24岁，考试得了100分。
```

继承通过**extends**关键字实现，子类可以调用父类public、protected、default的属性/方法，但无法访问父类private的属性/方法。
student.name 这句代码编译器将会报错。

**构造器：**

父类的构造器是带有参数的，则必须在子类的构造器中显示地通过super关键字调用父类的构造器并配以适当的当属列表。

**继承的优点：**

1. 代码复用性强。
2. 子类只需要关注自己的逻辑。
3. 多态的基础。

**继承的缺点：**

1. 一定意义上破坏了封装。
2. 继承是一种强耦合关系，父类变，子类就必须变。

**继承的替代方式：**

1. 组合。

**组合实例代码：**

```java
public class Teacher {

    private Person person = new Person();

}
```

组合是**has-a**的关系，继承是**is-a**的关系。

应当尽量使用组合而避免使用继承。

2. 接口。

**接口实例代码：**

```java
public interface IPersonService {

    void say();

}

public class PersonServiceImpl implements IPersonService {

    @Override
    public void say() {
        System.out.println("Hello World!");
    }
}
```

使用**interface**来定义接口。

使用**implements**来实现接口。

接口可以多实现。

**如何不让类被继承：**

利用final关键字修饰类。final类的方法也默认是final。

**多态性**
  多态性是指父类或接口定义的引用变量可以指向子类或具体实现类的实例对象，提高了程序的扩展性。简单来说就是：允许将子类类型的指针赋值给父类类型的指针。实现多态有两种方式，覆盖（重写）和重载。两者的区别在于：覆盖在运行时决定，重载是在编译时决定。并且覆盖和重载的机制不同。例如在Java中，重载方法的签名必须不同于原先方法的，但对于覆盖来说签名就必须相同。

**覆盖实例代码：**

```java
public interface IPersonService {

    void say();

}

public class PersonServiceImpl implements IPersonService {

    @Override
    public void say() {
        System.out.println("Hello World!");
    }
}
```

PersonServiceImpl覆盖了其实现类IPersonService的say()方法。

**重载实例代码：**

```java
public class PersonServiceImpl implements IPersonService {

    @Override
    public void say() {
        System.out.println("Hello World!");
    }

    public void say(String msg){
        System.out.println(msg);
    }
}
```

say(String msg)方法重载了say()。

重载方法的特点是方法名相同而参数签名不同。

- 被重载的方法必须改变参数签名。
- 被重载的方法可以改变返回类型。
- 被重载的方法可以改变访问修饰符。
- 被重载的方法可以声明新的或更广的检查异常。
- 方法能够在同一个类中或者在一个子类中被重载。

**向上转型与向下转型：**

**向上转型的好处**

1. 减少重复代码，使代码变得更简洁。
2. 提高系统扩展性。

**向上转型实例代码：**

```java
    public static void main(String[] args) {

        //向上转型
        Person person = new Student("corona",24,100);

    }
```

**向下转型的注意事项**

1. 向下转型的前提是父类的引用变量指向的是子类对象。（也就是说，在向下转型之前，它得先向上转型）
2. 向下转型只能转型为本类对象。（猫是不能变成人的）

**向下转型实例代码：**

```java
    public static void main(String[] args) {

        //向下转型（必须强制类型转换）
        Student student = (Student) new Person("corona",24);

    }
```

**五大基本原则：单一职责原则、开放封闭原则、里式替换原则、依赖倒置原则、接口分离原则。**

* 单一职责原则SRP（Single Responsibility Principle）：类的功能要单一，不要包罗万象。
* 开放封闭原则OCP（Open Close Principle）：一个模块对于扩展是开放的，对于修改是封闭的。
* 里式替换原则LSP（Liskov Substitution Principle）：子类可以替换父类出现在父类能够出现的任何地方。
* 依赖倒置原则DIP（Dependency Inversion Principle）：高层次的模块不应该依赖于低层次的模块，他们都应该依赖于抽象。抽象不应该依赖于具体实现，具体实现应该依赖于抽象。
* 接口分离原则ISP（Interface Segregation Principle）：设计时采用多个与特定客户类有关的接口比采用一个通用的接口要好。

## 二.平台无关性

### 1.什么是平台无关性？

平台无关（跨平台）：一种语言在计算机上的运行不受平台的约束，一次编译到处运行。

### 2.Java是如何做到平台无关性的？

Java经过编译之后生成的.class字节码文件，运行平台上只要有JVM就能运行，不需要进行再次编译。

### 3.JVM还支持哪些语言？

Java、kotlin、Scala、Clojure、Groovy、Jython、Ruby、Ceylon、Eta、Haxe等。

## 三.构造函数与默认构造函数

### 1. 不同

1. 创建主体上的不同：无参构造函数是开发者创建的，默认构造函数是由编译器生成的。
2. 创建方式上的不同：显示声明无参构造函数时，编译器不会生成默认构造函数。
3. 创建目的上的不同：开发者在类中声明无参构造函数，是为了对类进行初始化操作；而编译器生成默认构造函数，是为了在JVM进行类加载时，能够顺利验证父类的数据信息。

### 2. 构造函数的执行顺序

先父类再子类。

初始化时构造函数的调用顺序是这样的：

1. 按顺序调用父类成员变量和实例成员变量的初始化表达式；
2. 调用父类构造函数；
3. 按顺序分别调用类成员变量和实例成员变量的初始化表达式；
4. 调用类构造函数。

### 3. Java对象初始化中的构造函数

new关键字创建对象的方法，在Java规范中被称为由执行类实例创建表达式而引起的对象创建。

### 4.类构造器方法与实例构造器方法的不同

1. clinit，类构造器方法，在jvm第一次加载class文件时调用，因为是类级别的，所以只加载一次，是编译器自动收集类中所有类变量（static修饰的变量）和静态语句块（static{}），中的语句合并产生的，编译器收集的顺序，是由程序员在写在源文件中的代码的顺序决定的。
2. init，实例构造器方法，在实例创建出来的时候调用，包括调用new操作符；调用Class或java.lang.reflect.Constructor对象的newInstance()方法；调用任何现有对象的clone()方法；通过java.io.ObjectInputStream类的getObject()方法反序列化。

Java对象创建时有两种类型的构造函数：类构造函数方法、实例构造函数方法，整个Java对象的创建过程是这样的：
父类的类构造器方法clinit方法->子类的类构造器方法clinit方法->父类的实例变量和实例代码块->父类的构造函数->子类的实例变量和实例代码块->子类的构造函数。

## 四.基本数据类型

 Java分为两大数据类型：

- 内置数据类型
- 引用数据类型

### 1.内置数据类型（基本数据类型）

Java提供了8种内置数据类型。6种数字类型（四个整数型，两个浮点型），一种字符类型，还有一种布尔型。

- byte：1个字节，8位。默认值0，-128(-27)~127(27-1)。节约空间。
- short：2个字节，16位。默认值0，-32768~32767。节约空间。
- int：4个字节，32位。默认值0。整型变量默认为int类型。
- long：8个字节，64位。默认值0L。
- float：单精度、32位、符合IEEE754标准的浮点数。默认值0.0f。
- double：双精度、64位、符合IEEE754标准的浮点数。默认值0.0d。浮点数的默认类型为double。
- boolean：只有true和false。默认值false。
- char：单一的16位unicode字符。最小值是\u0000（即0），最大值是\uffff（即65535）。

对于数值类型的基本类型的取值范围，已经以常量的形式定义在对应的包装类中了。

### 2.引用数据类型

* 指向对象的变量是引用变量，存储的是对象的地址。
* 对象、数组都是引用数据类型。
* 所有引用类型的默认值都是null。

### 3.常量

常量在程序运行时是不能被修改的。 在Java中使用final关键字来修饰常量。

### 4.为什么不能用浮点型表示金额？

浮点数有误差，精度不准，在计算机实际处理和运算过程中，浮点数本质上是以二进制形式存在的。 而十进制的0.1在二进制下将是一个无限循环小数，这就会导致误差的出现。 如果一个小数不是2的负整数次幂，用浮点数表示必然产生浮点误差。 换言之：A进制下的有限小数，转换到B进制下极有可能是无限小数，误差也由此产生。

### 5.用BigDecimal表示金额

BigDecimal类可以表示任意精度的数字，原理是：用字符串存储数字，转换为数组来模拟大数，实现两个数组的数学运算并将结果返回。 使用要点：

- 传入BigDecimal的数字必须为String。
- 使用除法的时候应该指定小数位数和舍入模式。

## 五.自动拆箱与自动装箱

* 自动装箱: 就是将基本数据类型自动转换成对应的包装类。
* 自动拆箱：就是将包装类自动转换成对应的基本数据类型。

### 1.Integer的缓存机制

当需要进行自动装箱时，如果数字在-128至127之间时，会直接使用缓存中的对象，而不是重新创建一个对象。 可以通过java.lang.Integer.IntegerCache.high设置最大值。

所以当比较两个Integer对象的数值时候最好用equals函数，而不要使用==，因为数字在-128至127以外的Integer对象即使数值一致但由于变量指向的是不同对象的地址，因而==的比较结果也不会相等。

## 六.值传递与引用传递

Java只有值传递没有引用传递。

参考文章：[这一次，彻底解决Java的值传递和引用传递](https://juejin.im/post/6844903696996941832)，作者：假不理。

## 七.String深度解析

### 1. 什么是不可变对象

如果一个对象在创建之后就不能再改变它的状态，那么这个对象是不可变的（immutable）。不能改变状态的意思是，不能改变对象内的成员变量，包括基本数据类型变量的值不能改变，引用类型的变量不能指向其他的对象，引用类型指向的对象的状态也不能改变。

### 2. final关键字的作用

如果要创建一个不可变对象，关键一步就是要将所有的成员变量声明为final类型。

* final修饰类，则该类不能被继承，该类的所有方法自动地成为final方法。
* final修饰方法，表示子类不可重写该方法。
* final修饰基本数据类型变量，表示该变量为常量，值不能再修改。
* final修饰引用类型变量，表示该引用，表示该引用在构造对象之后不能指向其他的对象，但该引用指向的对象的状态可以改变。

### 3. String的不可变性

```java
public final class String
    implements java.io.Serializable, Comparable<String>, CharSequence {
    /** The value is used for character storage. */
    private final char value[];
    ......
}
```

首先可以看到，String类使用了final修饰符，表明String类是不可继承的。

然后，我们主要关注String类的成员变量value,value是char[]类型，因此String对象实际上是用这个字符数组进行封装的。再看value的修饰符，使用了private，也没有提供setter方法，所以在String类的外部不能修改value，同时value也使用了final进行修饰，那么在String类的内部也不能修改value，但是上面final修饰引用类型变量的内容提到，这只能保证value不能指向其他的对象，但value指向的对象的状态是可以改变的。

通过查看String类源码可以发现，String类不可变，关键是因为SUN公司的工程师，在后面所有String的方法里都很小心的没有去动字符数组里的元素。所以String类不可变的关键都在底层的实现，而不仅仅是一个final。

但是通过反射可以访问到private变量，所以通过反射是可以修改String这种不可变对象的。

### 4 .为什么String要设计成不可变的

#### 4.1 字符串常量池的需要

字符串常量池是Java堆内存中的一个特殊的存储区域，当用字符串字面量创或者intern()方法创建一个字符串对象的时候，假如此字符串值已经存在于常量池中，则不会创建一个新的对象，而是引用已经存在的对象。

#### 4.2 允许String对象缓存HashCode

```java
public final class String
    implements java.io.Serializable, Comparable<String>, CharSequence {

    ...

    /** 缓存哈希码 */
    private int hash; // 默认0
    
     /**
     * 返回此字符串的哈希码，该哈希码为以下算式的结果
     * <blockquote><pre>
     * s[0]*31^(n-1) + s[1]*31^(n-2) + ... + s[n-1]
     * </pre></blockquote>
     * s[i]是此字符串对应位置字符的ASCII编码，n是此字符串的长度也指数31的是幂值
     * (空字符串的哈希值为0.)
     *
     * @return  a hash code value for this object.
     */
    public int hashCode() {
        int h = hash;
        if (h == 0 && value.length > 0) {
            hash = h = isLatin1() ? StringLatin1.hashCode(value)
                                  : StringUTF16.hashCode(value);
        }
        return h;
    }
    
    
    ...
}

final class StringLatin1 {
    ...
    public static int hashCode(byte[] value) {
        int h = 0;
        for (byte v : value) {
            h = 31 * h + (v & 0xff);
        }
        return h;
    }
    ...
}
final class StringUTF16 {
    ...
    public static int hashCode(byte[] value) {
        int h = 0;
        int length = value.length >> 1;
        for (int i = 0; i < length; i++) {
            h = 31 * h + getChar(value, i);
        }
        return h;
    }
    ...
}
```

Java中String对象的哈希码被频繁地使用，比如在HashMap等容器中，字符串的不可变能保证其hashcode永远保持一致，这就意味着不必更新字符串的hashcode值，更加高效。

#### 4.3 安全性

String被广泛的使用在其他Java类中充当参数。比如网络连接、打开文件等操作。如果字符串可变，那么类似操作可能导致安全问题。

另外不可变对象天生就是线程安全的。

可以自由地在多个线程之间共享。不需要任何同步处理。

### 5. JDK6和JDK7中substring的原理及区别

#### 5.1 substring()的作用

`substring(int beginIndex, int endIndex)`方法截取字符串并返回其[beginIndex,endIndex-1]范围内的内容。

```java
public static void main(String[] args) {

    String s = "Corona Blogs";
    System.out.println(s.substring(0,s.length()-1));

}

输出结果：Corona Blog
```

#### 5.2 JDK6中的substring()

String是通过字符数组实现的。在jdk 6 中，String类包含三个成员变量：`char value[]`， `int offset`，`int count`。他们分别用来存储真正的字符数组，数组的第一个位置索引以及字符串中包含的字符个数。

当调用substring方法的时候，会创建一个新的string对象，但是这个string的值仍然指向堆中的同一个字符数组。这两个对象中只有count和offset 的值是不同的。

```java
//JDK 6
String(int offset, int count, char value[]) {
    this.value = value;
    this.offset = offset;
    this.count = count;
}

public String substring(int beginIndex, int endIndex) {
    //check boundary
    return  new String(offset + beginIndex, endIndex - beginIndex, value);
}
```

**导致的问题**

根据上述JDK6中实现substring的原理可知，我们需要的切割后的字符串长度总是小于等于原字符串长度,这就会导致性能问题。

在JDK 6中，一般用以下方式来解决该问题，即生成一个新的字符串并将对象指向新字符串。

```java
x = x.substring(x, y) + "";
```

#### 5.3 JDK7中的substring()

在JDK7中，substring方法会在堆内存中创建一个新的数组。

```java
//JDK 7
public String(char value[], int offset, int count) {
    //check boundary
    //复制数组（仅复制需要的部分）
    this.value = Arrays.copyOfRange(value, offset, offset + count);
}

public String substring(int beginIndex, int endIndex) {
    //check boundary
    int subLen = endIndex - beginIndex;
    return new String(value, beginIndex, subLen);
}
```

通过数组复制（按需）的方法，就不会造成内存浪费，便不存在性能问题。

### 6. replace、replaceAll、replaceFirst区别

* replace：仅支持字符、字符串参数进行替换，替换范围为全部替换。
* replaceAll：支持正则替换，替换范围为全部替换。
* replaceFirst：支持正则替换，替换范围为仅替换第一次出现的。

```java
public static void main(String[] args) {
    String s = "Corona Blogs";
    System.out.println("replace：" + s.replace('o', 'b'));
    System.out.println("replaceAll：" + s.replaceAll("[o]", "b"));
    System.out.println("replaceFirst：" + s.replaceFirst("[o]", "b"));
}
输出结果：
replace：Cbrbna Blbgs
replaceAll：Cbrbna Blbgs
replaceFirst：Cbrona Blogs
```

### 7. String对“+”的重载

#### 7.1 重载的概念

重载(overloading) 是在一个类里面，方法名字相同，而参数不同。返回类型可以相同也可以不同。

#### 7.2 JDK8中对“+”的重载

java中实际没有运算符的重载，但是对String对象而言，它是可以直接`+`将两个String对象的字符串值相加。乍看起来这是对`+`的重载，但我们可以通过class文件看出，这只是JVM做的语法糖。

```java
public static void main(String[] args) {
    String s1 = "Corona";
    String s2 = "Blog";
    String s3 = s1 + s2;
    System.out.println(s3);
}
```

反编译代码如下：

```java
C:\Users\12272\Desktop\Corona\src\com\corona>javac Test.java

C:\Users\12272\Desktop\Corona\src\com\corona>javap -c Test
Compiled from "Test.java"
public class com.corona.Test {
  public com.corona.Test();
    Code:
       0: aload_0
       1: invokespecial #1                  // Method java/lang/Object."<init>":()V
       4: return

public static void main(java.lang.String[]);
    Code:
       0: ldc           #2                  // String Corona
       2: astore_1
       3: ldc           #3                  // String Blog
       5: astore_2
       6: new           #4                  // class java/lang/StringBuilder
       9: dup
      10: invokespecial #5                  // Method java/lang/StringBuilder."<
init>":()V
      13: aload_1
      14: invokevirtual #6                  // Method java/lang/StringBuilder.append:(Ljava/lang/String;)Ljava/lang/StringBuilder;
      17: aload_2
      18: invokevirtual #6                  // Method java/lang/StringBuilder.append:(Ljava/lang/String;)Ljava/lang/StringBuilder;
      21: invokevirtual #7                  // Method java/lang/StringBuilder.toString:()Ljava/lang/String;
      24: astore_3
      25: getstatic     #8                  // Field java/lang/System.out:Ljava/io/PrintStream;
      28: new           #4                  // class java/lang/StringBuilder
      31: dup
      32: invokespecial #5                  // Method java/lang/StringBuilder."<init>":()V
      35: ldc           #9                  // String str3:
      37: invokevirtual #6                  // Method java/lang/StringBuilder.append:(Ljava/lang/String;)Ljava/lang/StringBuilder;
      40: aload_3
      41: invokevirtual #6                  // Method java/lang/StringBuilder.append:(Ljava/lang/String;)Ljava/lang/StringBuilder;
      44: invokevirtual #7                  // Method java/lang/StringBuilder.toString:()Ljava/lang/String;
      47: invokevirtual #10                 // Method java/io/PrintStream.println:(Ljava/lang/String;)V
      50: return
}
```

可见其实String对`+`的支持其实就是使用了**StringBuilder**以及他的**append**、**toString**两个方法。

#### 7.3 JDK9中对“+”的重载

```java
public static void main(String[] args) {
    String s1 = "Corona";
    String s2 = "Blog";
    String s3 = s1 + s2;
    System.out.println(s3);
}
```

反编译代码如下：

```java
C:\Users\12272\Desktop\Corona\src\com\corona>javac Test.java

C:\Users\12272\Desktop\Corona\src\com\corona>javap -c Test
Compiled from "Test.java"
public class com.corona.Test {
  public com.corona.Test();
    Code:
       0: aload_0
       1: invokespecial #1                  // Method java/lang/Object."<init>":()V
       4: return

  public static void main(java.lang.String[]);
    Code:
       0: ldc           #2                  // String Corona
       2: astore_1
       3: ldc           #3                  // String Blog
       5: astore_2
       6: aload_1
       7: aload_2
       8: invokedynamic #4,  0              // InvokeDynamic #0:makeConcatWithConstants:(Ljava/lang/String;Ljava/lang/String;)Ljava/lang/String;
      13: astore_3
      14: getstatic     #5                  // Field java/lang/System.out:Ljava/io/PrintStream;
      17: aload_3
      18: invokevirtual #6                  // Method java/io/PrintStream.println:(Ljava/lang/String;)V
      21: return
}

```

我们可以看到，JAVA 9用的是动态调用。

**关于动态调用tips**

- invokestatic　　//调用静态方法
- invokespecial　　//调用私有方法、实例构造器方法、父类方法
- invokevirtual　　//调用实例方法
- invokeinterface　　//调用接口方法，会在运行时再确定一个实现此接口的对象
- **invokedynamic**　　//先在运行时动态解析出调用点限定符所引用的方法，然后再执行该方法，在此之前的4条调用指令，分派逻辑是固化在java虚拟机内部的，而invokedynamic指令的分派逻辑是由用户所设定的引导方法决定的。

### 8. 字符串拼接的几种方式

#### 8.1 使用运算符“+”

```java
String s1 = "Corona" + "Blog";
```

#### 8.2 使用concat()

```java
String s1 = "Corona".concat("Blog");
```

concat源码：

```java
    public String concat(String str) {
        int olen = str.length();
        //如果要拼接的目标字符串长度为0，则返回源字符串即可
        if (olen == 0) {
            return this;
        }
        //如果源字符串与要目标字符串编码一致，则执行
        if (coder() == str.coder()) {
            //创建一个数组val，将源字符串的字节数组赋值给val
            byte[] val = this.value;
            //创建一个数组oval，将目标字符串的字节数组赋值给oval
            byte[] oval = str.value;
            //长度是val和oval的长度之和
            int len = val.length + oval.length;
            //创建一个数组buf，长度为val和oval的长度之和，并将val的字节数组复制给buf
            byte[] buf = Arrays.copyOf(val, len);
            //将oval的字节数组复制给buf
            System.arraycopy(oval, 0, buf, val.length, oval.length);
            //返回新的String对象
            return new String(buf, coder);
        }
        //获取源字符串数字长度
        int len = length();
        //创建一个数组buf，长度为源字符串与目标字符串的长度之和
        byte[] buf = StringUTF16.newBytesFor(len + olen);
        //将源字符串的字节数组复制给buf
        getBytes(buf, 0, UTF16);
        //将目标字符串的字节数组复制给buf
        str.getBytes(buf, len, UTF16);
        //返回新的String对象
        return new String(buf, UTF16);
    }

    /**
     * System.arraycopy()是一个本地方法
     * src：源数组
     * srcPos：源数组的起始位置
     * dest：目标数组
     * destPos：目标数组的起始位置
     * length：要拷贝的数组的元素数量
     */
    @HotSpotIntrinsicCandidate
    public static native void arraycopy(Object src,  int  srcPos,
                                        Object dest, int destPos,
                                        int length);
```

#### 8.3 使用StringBuffer

```java
StringBuilder s = new StringBuilder();
s.append("Corona");
s.append("Blog");
```

通过append方法进行拼接。

源码：

```java
    public AbstractStringBuilder append(String str) {
        //如果要追加的对象是null，则为其追加'n'、'u'、'l'、'l'四个字符
        if (str == null) {
            return appendNull();
        }
        //获得源StringBuffer的长度
        int len = str.length();
        //确保StringBuffer的长度能容纳要追加的字符串
        ensureCapacityInternal(count + len);
        //追加字符串
        putStringAt(count, str);
        count += len;
        return this;
    }

    private AbstractStringBuilder appendNull() {
        //增加4的容量，以容纳字符串null
        ensureCapacityInternal(count + 4);
        int count = this.count;
        byte[] val = this.value;
        //如果源字符串是Latin1编码（ISO-8859-1）且为紧凑字符串，则为其字节数组添加null四个字符
        if (isLatin1()) {
            val[count++] = 'n';
            val[count++] = 'u';
            val[count++] = 'l';
            val[count++] = 'l';
        } else {
            //追加null四个字符
            count = StringUTF16.putCharsAt(val, count, 'n', 'u', 'l', 'l');
        }
        this.count = count;
        return this;
    }

    private void ensureCapacityInternal(int minimumCapacity) {
        // overflow-conscious code
        //求出旧容量oldCapacity
        int oldCapacity = value.length >> coder;
        //如果原本的容量oldCapacity小于拼接后所需要满足的最小容量minimumCapacity，则对其进行扩充，扩充完的长度为minimumCapacity
        if (minimumCapacity - oldCapacity > 0) {
            value = Arrays.copyOf(value,
                    newCapacity(minimumCapacity) << coder);
        }
    }

    //判断字符串是否Latin1编码（ISO-8859-1）且为紧凑字符串
    final boolean isLatin1() {
        return COMPACT_STRINGS && coder == LATIN1;
    }

    //追加四个字符
    public static int putCharsAt(byte[] value, int i, char c1, char c2, char c3, char c4) {
        int end = i + 4;
        checkBoundsBeginEnd(i, end, value);
        putChar(value, i++, c1);
        putChar(value, i++, c2);
        putChar(value, i++, c3);
        putChar(value, i++, c4);
        assert(i == end);
        return end;
    }

    //追加字符串
    private final void putStringAt(int index, String str) {
        //如果源字符串与目标字符串的编码不一致，则需要将源字符串的编码改为UTF16
        if (getCoder() != str.coder()) {
            inflate();
        }
        //
        str.getBytes(value, index, coder);
    }

    /**
     * 如果源字符串是 "isLatin1()",则将其置为UTF编码，从8位字节转为16位字节
     */
    private void inflate() {
        //如果源字符串不是 "isLatin1()"（不是iso则必是UTF），直接返回
        if (!isLatin1()) {
            return;
        }
        //创建一个UTF16编码的字节数组buf，长度为源字符串的长度
        byte[] buf = StringUTF16.newBytesFor(value.length);
        //将源字符串的字节数组复制给buf
        StringLatin1.inflate(value, 0, buf, 0, count);
        this.value = buf;
        //将编码置为UTF16
        this.coder = UTF16;
    }

    /**
     * 复制字节数组
     */
    void getBytes(byte dst[], int dstBegin, byte coder) {
        //如果编码一致，则直接通过native方法arraycopy将目标字节数组的值复制给源字节数组
        if (coder() == coder) {
            System.arraycopy(value, 0, dst, dstBegin << coder, value.length);
        } else {    // this.coder == LATIN && coder == UTF16
            //否则
            StringLatin1.inflate(value, 0, dst, dstBegin, value.length);
        }
    }

    @HotSpotIntrinsicCandidate
    public static void inflate(byte[] src, int srcOff, byte[] dst, int dstOff, int len) {
        StringUTF16.inflate(src, srcOff, dst, dstOff, len);
    }

    public static void inflate(byte[] src, int srcOff, byte[] dst, int dstOff, int len) {
        // We need a range check here because 'putChar' has no checks
        checkBoundsOffCount(dstOff, len, dst);
        for (int i = 0; i < len; i++) {
            putChar(dst, dstOff++, src[srcOff++] & 0xff);
        }
    }
```

#### 8.4 使用StringBuilder

```java
StringBuilder s = new StringBuilder();
s.append("Corona");
s.append("Blog");
```

通过append方法进行拼接。

源码解析参考StringBuffer。

#### 8.5 使用String.join()

```java
List<String> names = new ArrayList<>();
names.add("黄前久美子");
names.add("结城明日奈");
names.add("水原千鹤");
String fullName = String.join(",",names);
System.out.println(fullName);

输出结果：黄前久美子,结城明日奈,水原千鹤
```

主要通过StringJoiner类实现。

源码：

```java
public final class StringJoiner {
    //前缀
    private final String prefix;
    //分隔符
    private final String delimiter;
    //后缀
    private final String suffix;

    /** StringJoiner中存放字符串的数组 */
    private String[] elts;
    
    /** 被添加到elts数组中元素的个数 **/
    private int size;
    
    /** 总长度，包括前缀和后缀 */
    private int len;
    
    private String emptyValue;
    
    public static String join(CharSequence delimiter,
            Iterable<? extends CharSequence> elements) {
        //分隔符delimiter不能为空
        Objects.requireNonNull(delimiter);
        //集合elements不能为空
        Objects.requireNonNull(elements);
        //创建一个StringJoiner对象joiner，并赋予分隔符delimiter
        StringJoiner joiner = new StringJoiner(delimiter);
        //在joiner中循环追加集合元素
        for (CharSequence cs: elements) {
            joiner.add(cs);
        }
        //返回字符串对象
        return joiner.toString();
    }

    public StringJoiner(CharSequence delimiter) {
        this(delimiter, "", "");
    }

    public StringJoiner(CharSequence delimiter,
                        CharSequence prefix,
                        CharSequence suffix) {
        Objects.requireNonNull(prefix, "The prefix must not be null");
        Objects.requireNonNull(delimiter, "The delimiter must not be null");
        Objects.requireNonNull(suffix, "The suffix must not be null");
        // make defensive copies of arguments
        this.prefix = prefix.toString();
        this.delimiter = delimiter.toString();
        this.suffix = suffix.toString();
    }

    //StringJoiner中追加字符串的方法
    //CharSequence是一个描述字符串结构的接口，在这个接口里面一般发现有三种常用的子类：String、StringBuffer、StringBuilder
    public StringJoiner add(CharSequence newElement) {
        //将要追加的元素转为String对象elt
        final String elt = String.valueOf(newElement);
        //如果elts为空（elts为StringJoiner中存放字符串的数组）
        if (elts == null) {
            //初始化数组长度为8
            elts = new String[8];
        } else {
            //如果elts数组中的元素个数与elts的长度一致，则将elts的数组容量扩大一倍
            if (size == elts.length)
                //将elts的数组容量扩大一倍
                elts = Arrays.copyOf(elts, 2 * size);
            //总长度还需要加上分隔符的长度
            len += delimiter.length();
        }
        //总长度加上要追加的String对象elt的长度
        len += elt.length();
        //在etls数组中追加String对象elt
        elts[size++] = elt;
        return this;
    }
    
    //返回字符串对象
    public String toString() {
        final String[] elts = this.elts;
        if (elts == null && emptyValue != null) {
            return emptyValue;
        }
        final int size = this.size;
        final int addLen = prefix.length() + suffix.length();
        if (addLen == 0) {
            compactElts();
            return size == 0 ? "" : elts[0];
        }
        final String delimiter = this.delimiter;
        final char[] chars = new char[len + addLen];
        int k = getChars(prefix, chars, 0);
        if (size > 0) {
            //先追加一个元素字符
            k += getChars(elts[0], chars, k);
            //循环遍历追加分隔符与元素字符
            for (int i = 1; i < size; i++) {
                k += getChars(delimiter, chars, k);
                k += getChars(elts[i], chars, k);
            }
        }
        k += getChars(suffix, chars, k);
        return new String(chars);
    }
}
```



#### 8.6 StringBuffer与StringBuilder的区别

StringBuffer线程安全，效率较低。

StringBuilder线程不安全，效率较高。

源码：

```java
	
 public final class StringBuffer
    extends AbstractStringBuilder
    implements java.io.Serializable, Comparable<StringBuffer>, CharSequence
{
     ...
	@Override
    public synchronized int compareTo(StringBuffer another) {
        return super.compareTo(another);
    }

    @Override
    public synchronized int length() {
        return count;
    }

    @Override
    public synchronized int capacity() {
        return super.capacity();
    }


    @Override
    public synchronized void ensureCapacity(int minimumCapacity) {
        super.ensureCapacity(minimumCapacity);
    }

    /**
     * @since      1.5
     */
    @Override
    public synchronized void trimToSize() {
        super.trimToSize();
    }
    ...
}
```

可以看见StringBuffer中相当多的方法都加了synchronized关键字，这是java的一个内置锁。

### 9. String.valueOf和Integer.toString的区别

没区别。

源码：

```java
public final class String
    implements java.io.Serializable, Comparable<String>, CharSequence {
    ...
    public static String valueOf(int i) {
        return Integer.toString(i);
    }
    ...
}
```

可见，对于整型来说，无论是通过String.valueOf还是Integer.toString转化为字符串，底层都是通过Integer.toString()方法。

### 10. switch对String的支持

编译后的class代码：

```java
public class Test {
    public Test() {
    }

    public static void main(String[] var0) {
        String var1 = "Corona Blog";
        byte var3 = -1;
        //由此处可知，是通过String的hashCode值替代String的字符串值
        switch(var1.hashCode()) {
        case -862545276:
            //通过equals比较
            if (var1.equals("Hello World")) {
                var3 = 1;
            }
            break;
        case 1462031910:
            if (var1.equals("Corona Blog")) {
                var3 = 0;
            }
        }

        switch(var3) {
        case 0:
            System.out.println("Corona Blog");
            break;
        case 1:
            System.out.println("Hello World");
            break;
        default:
            System.out.println("Nothing");
        }

    }
}

```

由字节码可知，jdk7中新增的switch对字符串的支持是通过hashcode值与equals()方法实现的。

### 11. 扩展

有关 字符串池、常量池（运行时常量池、Class常量池），以及intern()等相关知识统一放到JVM讲。

